collective.documentgenerator-4.0-py3.12-nspkg.pth
collective/documentgenerator/DX_renderer.py
collective/documentgenerator/__init__.py
collective/documentgenerator/adapters.py
collective/documentgenerator/config.py
collective/documentgenerator/configure.zcml
collective/documentgenerator/interfaces.py
collective/documentgenerator/profiles.zcml
collective/documentgenerator/renderer.zcml
collective/documentgenerator/setuphandlers.py
collective/documentgenerator/testing.py
collective/documentgenerator/testing.zcml
collective/documentgenerator/utils.py
collective/documentgenerator/browser/__init__.py
collective/documentgenerator/browser/actionspanel.py
collective/documentgenerator/browser/check_pod_templates.pt
collective/documentgenerator/browser/children_pod_template.pt
collective/documentgenerator/browser/configure.zcml
collective/documentgenerator/browser/controlpanel.py
collective/documentgenerator/browser/generation_view.py
collective/documentgenerator/browser/overrides.py
collective/documentgenerator/browser/table.py
collective/documentgenerator/browser/templates_listing.pt
collective/documentgenerator/browser/views.py
collective/documentgenerator/browser/resources/css/documentgenerator.css
collective/documentgenerator/browser/static/.gitkeep
collective/documentgenerator/browser/static/configurable.svg
collective/documentgenerator/browser/static/csv.svg
collective/documentgenerator/browser/static/doc.svg
collective/documentgenerator/browser/static/docx.svg
collective/documentgenerator/browser/static/download_icon.svg
collective/documentgenerator/browser/static/libreoffice-blanck.svg
collective/documentgenerator/browser/static/mailinglooptemplate.svg
collective/documentgenerator/browser/static/missing_use.svg
collective/documentgenerator/browser/static/nok.svg
collective/documentgenerator/browser/static/nok_use.svg
collective/documentgenerator/browser/static/nok_used.svg
collective/documentgenerator/browser/static/odp.svg
collective_documentgenerator-4.0.dist-info/METADATA
collective_documentgenerator-4.0.dist-info/WHEEL
collective_documentgenerator-4.0.dist-info/entry_points.txt
collective_documentgenerator-4.0.dist-info/namespace_packages.txt
collective_documentgenerator-4.0.dist-info/top_level.txt
collective_documentgenerator-4.0.dist-info/RECORD
