Metadata-Version: 2.4
Name: collective.documentgenerator
Version: 4.0
Summary: Desktop document generation (.odt, .pdf, .doc, ...) based on appy framework (https://appyframe.work/tool/public) and OpenOffice/LibreOffice
Home-page: https://pypi.org/project/collective.documentgenerator
Author: Simon Delcourt
Author-email: simon.delcourt@imio.be
License: GPL
Keywords: plone document generation generator odt word pdf libreoffice template
Classifier: Environment :: Web Environment
Classifier: Framework :: Plone
Classifier: Framework :: Plone :: Addon
Classifier: Framework :: Plone :: 6.0
Classifier: Framework :: Plone :: 6.1
Classifier: Framework :: Plone :: Addon
Classifier: License :: OSI Approved :: GNU General Public License (GPL)
Classifier: Programming Language :: Python
Classifier: Programming Language :: Python :: 3.10
Classifier: Programming Language :: Python :: 3.13
Requires-Dist: appy>=1.0.4
Requires-Dist: beautifulsoup4
Requires-Dist: collective.behavior.talcondition
Requires-Dist: collective.excelexport
Requires-Dist: collective.z3cform.datagridfield
Requires-Dist: future>=0.14.0
Requires-Dist: imio.migrator>=1.11
Requires-Dist: phonenumbers
Requires-Dist: plone.api>=1.3.3
Requires-Dist: plone.app.dexterity
Requires-Dist: plone.app.lockingbehavior
Requires-Dist: setuptools
Requires-Dist: z3c.table
Requires-Dist: z3c.form>=3.2.4
Requires-Dist: imio.helpers>=1.0
Provides-Extra: test
Requires-Dist: plone.app.robotframework; extra == "test"
Requires-Dist: plone.app.testing; extra == "test"
Requires-Dist: imio.pyutils; extra == "test"
Dynamic: author
Dynamic: author-email
Dynamic: classifier
Dynamic: description
Dynamic: home-page
Dynamic: keywords
Dynamic: license
Dynamic: provides-extra
Dynamic: requires-dist
Dynamic: summary
